fir/__init__.py
fir/http.py
fir/wsgi.py
pyfir-0.0.7.dist-info/LICENSE
pyfir-0.0.7.dist-info/METADATA
pyfir-0.0.7.dist-info/WHEEL
pyfir-0.0.7.dist-info/top_level.txt
pyfir-0.0.7.dist-info/RECORD
