Metadata-Version: 2.1
Name: pyfir
Version: 0.0.7
Summary: Module to ease WSGI App testing.
Home-page: https://github.com/Claudjos/fir
Author: Claudjos
Author-email: claudjosmail@gmail.com
License: UNKNOWN
Keywords: Web App,Testing
Platform: UNKNOWN
License-File: LICENSE
